beanhub_forms/__init__.py
beanhub_forms/data_types/__init__.py
beanhub_forms/data_types/form.py
beanhub_forms/data_types/processor.py
beanhub_forms/form.py
beanhub_forms/processor.py
beanhub_forms-0.1.3.dist-info/LICENSE
beanhub_forms-0.1.3.dist-info/METADATA
beanhub_forms-0.1.3.dist-info/WHEEL
beanhub_forms-0.1.3.dist-info/RECORD
