Metadata-Version: 2.1
Name: beanhub-forms
Version: 0.1.3
Summary: Library for generating BeanHub's custom forms
License: MIT
Author: Fang-Pen Lin
Author-email: fangpen@launchplatform.com
Requires-Python: >=3.9,<4.0
Classifier: License :: OSI Approved :: MIT License
Classifier: Programming Language :: Python :: 3
Classifier: Programming Language :: Python :: 3.9
Classifier: Programming Language :: Python :: 3.10
Classifier: Programming Language :: Python :: 3.11
Requires-Dist: jinja2 (>=3.1.2,<4.0.0)
Requires-Dist: pydantic (>=2.4.0,<3.0.0)
Requires-Dist: pyyaml (>=6.0.1,<7.0.0)
Requires-Dist: wtforms (>=3.0.1,<4.0.0)
